loomaa/__init__.py
loomaa/__main__.py
loomaa/_bootstrap.py
loomaa/auth.py
loomaa/cli.py
loomaa/compiler.py
loomaa/compiler_pydantic.py
loomaa/deploy.py
loomaa/model.py
loomaa/models_pydantic.py
loomaa/utils.py
loomaa/validate.py
loomaa/viewer.py
loomaa-0.1.1.dist-info/licenses/LICENSE
loomaa-0.1.1.dist-info/METADATA
loomaa-0.1.1.dist-info/WHEEL
loomaa-0.1.1.dist-info/entry_points.txt
loomaa-0.1.1.dist-info/top_level.txt
loomaa-0.1.1.dist-info/RECORD
