Metadata-Version: 2.4
Name: loomaa
Version: 0.1.1
Summary: DevOps-native semantic model compiler for Microsoft Fabric
Author: Abiodun Adenugba
License: Apache-2.0
Classifier: Development Status :: 3 - Alpha
Classifier: Intended Audience :: Developers
Classifier: License :: OSI Approved :: Apache Software License
Classifier: Programming Language :: Python :: 3
Classifier: Programming Language :: Python :: 3.8
Classifier: Programming Language :: Python :: 3.9
Classifier: Programming Language :: Python :: 3.10
Classifier: Programming Language :: Python :: 3.11
Classifier: Programming Language :: Python :: 3.12
Requires-Python: >=3.8
License-File: LICENSE
Requires-Dist: typer>=0.9.0
Requires-Dist: pydantic>=2.0.0
Requires-Dist: jinja2>=3.1.0
Requires-Dist: requests>=2.31.0
Requires-Dist: msal>=1.27.0
Requires-Dist: streamlit>=1.28.0
Requires-Dist: plotly>=5.17.0
Requires-Dist: networkx>=3.2.0
Requires-Dist: pandas>=2.0.0
Dynamic: author
Dynamic: classifier
Dynamic: description
Dynamic: description-content-type
Dynamic: license
Dynamic: license-file
Dynamic: requires-dist
Dynamic: requires-python
Dynamic: summary
